char_count_package/__init__.py
char_count_package/main.py
char_count_package-0.0.2.dist-info/LICENSE
char_count_package-0.0.2.dist-info/METADATA
char_count_package-0.0.2.dist-info/WHEEL
char_count_package-0.0.2.dist-info/top_level.txt
char_count_package-0.0.2.dist-info/RECORD
