Metadata-Version: 2.1
Name: char_count_package
Version: 0.0.2
Summary: A package to count the ocurrency of unique characters in a string or file.
Author-email: Suelen Karbivnychyy <author@example.com>
Project-URL: Homepage, https://github.com/pypa/sampleproject
Project-URL: Issues, https://github.com/pypa/sampleproject/issues
Classifier: Programming Language :: Python :: 3
Classifier: License :: OSI Approved :: MIT License
Classifier: Operating System :: OS Independent
Requires-Python: >=3.8
License-File: LICENSE
